pytsammalex/__init__.py
pytsammalex/__main__.py
pytsammalex/ecoregions.json
pytsammalex/gbif.py
pytsammalex/lexibank.py
pytsammalex/clld/__init__.py
pytsammalex/clld/adapters.py
pytsammalex/clld/load.py
pytsammalex/clld/maps.py
pytsammalex/clld/models.py
pytsammalex/commands/__init__.py
pytsammalex/commands/gbif.py
pytsammalex-0.1.0.dist-info/LICENSE.txt
pytsammalex-0.1.0.dist-info/METADATA
pytsammalex-0.1.0.dist-info/RECORD
pytsammalex-0.1.0.dist-info/WHEEL
pytsammalex-0.1.0.dist-info/entry_points.txt
pytsammalex-0.1.0.dist-info/top_level.txt
